codemie_tools/__init__.py
codemie_tools/access_management/__init__.py
codemie_tools/access_management/keycloak/__init__.py
codemie_tools/access_management/keycloak/keycloak_client.py
codemie_tools/access_management/keycloak/models.py
codemie_tools/access_management/keycloak/tools.py
codemie_tools/access_management/keycloak/tools_vars.py
codemie_tools/access_management/toolkit.py
codemie_tools/azure_devops/__init__.py
codemie_tools/azure_devops/attachment_mixin.py
codemie_tools/azure_devops/test_plan/__init__.py
codemie_tools/azure_devops/test_plan/models.py
codemie_tools/azure_devops/test_plan/toolkit.py
codemie_tools/azure_devops/test_plan/tools.py
codemie_tools/azure_devops/test_plan/tools_vars.py
codemie_tools/azure_devops/wiki/__init__.py
codemie_tools/azure_devops/wiki/models.py
codemie_tools/azure_devops/wiki/toolkit.py
codemie_tools/azure_devops/wiki/tools.py
codemie_tools/azure_devops/wiki/tools_vars.py
codemie_tools/azure_devops/work_item/__init__.py
codemie_tools/azure_devops/work_item/models.py
codemie_tools/azure_devops/work_item/toolkit.py
codemie_tools/azure_devops/work_item/tools.py
codemie_tools/azure_devops/work_item/tools_vars.py
codemie_tools/base/__init__.py
codemie_tools/base/base_toolkit.py
codemie_tools/base/codemie_tool.py
codemie_tools/base/constants.py
codemie_tools/base/errors.py
codemie_tools/base/file_object.py
codemie_tools/base/file_tool_mixin.py
codemie_tools/base/models.py
codemie_tools/base/string_serializer.py
codemie_tools/base/toolkit_provider.py
codemie_tools/base/utils.py
codemie_tools/cloud/__init__.py
codemie_tools/cloud/aws/__init__.py
codemie_tools/cloud/aws/aws_client.py
codemie_tools/cloud/aws/models.py
codemie_tools/cloud/aws/tools.py
codemie_tools/cloud/aws/tools_vars.py
codemie_tools/cloud/azure/__init__.py
codemie_tools/cloud/azure/azure_client.py
codemie_tools/cloud/azure/models.py
codemie_tools/cloud/azure/tools.py
codemie_tools/cloud/azure/tools_vars.py
codemie_tools/cloud/gcp/__init__.py
codemie_tools-0.1.13.7.dist-info/LICENSE.txt
codemie_tools-0.1.13.7.dist-info/METADATA
codemie_tools-0.1.13.7.dist-info/WHEEL
codemie_tools-0.1.13.7.dist-info/RECORD
