Metadata-Version: 2.1
Name: codemie-tools
Version: 0.1.13.7
Summary: Package with CodeMie tools for AI Agents
Author: CodeMie Team
Author-email: codemie@epam.com
Requires-Python: >=3.12,<3.14
Classifier: Programming Language :: Python :: 3
Requires-Dist: PyGithub (>=2.2.0,<3.0.0)
Requires-Dist: atlassian-python-api (>=4.0.6,<5.0.0)
Requires-Dist: azure-core (>=1.30.2,<2.0.0)
Requires-Dist: azure-devops (==7.1.0b4)
Requires-Dist: azure-identity (>=1.16.0,<2.0.0)
Requires-Dist: boto3 (>=1.34.147,<2.0.0)
Requires-Dist: chardet (>=5.2.0,<6.0.0)
Requires-Dist: clevercsv (>=0.8.3,<0.9.0)
Requires-Dist: docx2txt (>=0.8,<0.9)
Requires-Dist: elastic-transport (==8.17.1)
Requires-Dist: elasticsearch (==8.18.1)
Requires-Dist: flake8 (>=7.1.1,<8.0.0)
Requires-Dist: gitpython (>=3.1.32,<4.0.0)
Requires-Dist: google-api-python-client (>=2.137.0,<3.0.0)
Requires-Dist: google-auth (>=2.32.0,<3.0.0)
Requires-Dist: googlemaps (>=4.10.0,<5.0.0)
Requires-Dist: httpx (>=0.28.1,<0.29.0)
Requires-Dist: influxdb-client (>=1.48.0,<2.0.0)
Requires-Dist: ipykernel (>=6.25.2,<7.0.0)
Requires-Dist: jupyter-kernel-gateway (>=3.0.1,<4.0.0)
Requires-Dist: kubernetes (>=34.1.0,<35.0.0)
Requires-Dist: langchain (==0.3.25)
Requires-Dist: langchain-community (==0.3.24)
Requires-Dist: langchain-core (==0.3.67)
Requires-Dist: langchain-experimental (==0.3.4)
Requires-Dist: langchain-google-community (==2.0.7)
Requires-Dist: langchain-openai (==0.3.17)
Requires-Dist: llm-sandbox[k8s] (>=0.3.21,<0.4.0)
Requires-Dist: markdown (>=3.8,<4.0)
Requires-Dist: markdownify (>=1.2.0,<2.0.0)
Requires-Dist: markitdown[all] (>=0.1.2,<0.2.0)
Requires-Dist: matplotlib (>=3.9.1,<4.0.0)
Requires-Dist: msrest (==0.7.1)
Requires-Dist: openapi-schema-pydantic (>=1.2.4,<2.0.0)
Requires-Dist: opencv-python-headless (>=4.11.0.86,<5.0.0.0)
Requires-Dist: openhands_aci (==0.1.2)
Requires-Dist: pandas (>=2.2.2,<3.0.0)
Requires-Dist: psycopg[binary,pool] (>=3.2.9,<4.0.0)
Requires-Dist: pydantic (>=2.9.2,<3.0.0)
Requires-Dist: pydantic-settings (>=2.5.2,<3.0.0)
Requires-Dist: pymssql (==2.2.11)
Requires-Dist: pymupdf4llm (>=0.0.24,<0.0.25)
Requires-Dist: pymysql (>=1.1.1,<2.0.0)
Requires-Dist: python-docx (>=1.1.0,<2.0.0)
Requires-Dist: python-dotenv (>=1.0.0,<2.0.0)
Requires-Dist: python-gitlab (>=4.6.0,<5.0.0)
Requires-Dist: python-pptx (>=1.0.2,<2.0.0)
Requires-Dist: sqlalchemy (>=2.0.35,<3.0.0)
Requires-Dist: tabulate (>=0.9.0,<0.10.0)
Requires-Dist: tiktoken (>=0.9.0,<0.10.0)
Requires-Dist: wikipedia (>=1.4.0,<2.0.0)
Requires-Dist: zephyr-python-api (>=0.1.0,<0.2.0)
